steam_api_zestx5/__init__.py
steam_api_zestx5/steamapi.py
steam_api_zestx5-0.0.5.dist-info/METADATA
steam_api_zestx5-0.0.5.dist-info/WHEEL
steam_api_zestx5-0.0.5.dist-info/licenses/LICENSE
steam_api_zestx5-0.0.5.dist-info/RECORD
