Metadata-Version: 2.3
Name: steam_api_zestx5
Version: 0.0.5
Summary: A small api wrapper
Project-URL: Homepage, https://github.com/zestx5/steamapi
Author-email: Ilya Buyankov <buyankov.ilya@gmail.com>
License-File: LICENSE
Classifier: License :: OSI Approved :: MIT License
Classifier: Operating System :: OS Independent
Classifier: Programming Language :: Python :: 3
Requires-Python: >=3.8
Requires-Dist: python-dotenv>=1.0.1
Requires-Dist: requests>=2.32.3
